pelican/plugins/statistics/__init__.py
pelican/plugins/statistics/readability.py
pelican/plugins/statistics/statistics.py
pelican/plugins/statistics/test_statistics.py
pelican_statistics-1.0.0.dist-info/METADATA
pelican_statistics-1.0.0.dist-info/WHEEL
pelican_statistics-1.0.0.dist-info/entry_points.txt
pelican_statistics-1.0.0.dist-info/RECORD
